{"48": {"becameSuitTime": 1551148398.38, "savedBy": null, "track": "c", "numFloors": "5", "difficulty": "7", "state": "suit", "block": "48"}, "50": {"becameSuitTime": 1551148398.383, "savedBy": null, "track": "l", "numFloors": "4", "difficulty": "7", "state": "suit", "block": "50"}, "51": {"becameSuitTime": 1551148398.38, "savedBy": null, "track": "l", "numFloors": "3", "difficulty": "5", "state": "suit", "block": "51"}, "12": {"becameSuitTime": 1551148398.38, "savedBy": null, "track": "l", "numFloors": "4", "difficulty": "5", "state": "suit", "block": "12"}, "22": {"becameSuitTime": 1551148398.38, "savedBy": null, "track": "c", "numFloors": "4", "difficulty": "7", "state": "suit", "block": "22"}}