{"26": {"becameSuitTime": 1551215076.348, "savedBy": null, "track": "m", "numFloors": "3", "difficulty": "3", "state": "suit", "block": "26"}, "25": {"becameSuitTime": 1551215089.677, "savedBy": null, "track": "m", "numFloors": "2", "difficulty": "4", "state": "suit", "block": "25"}, "18": {"becameSuitTime": 1551214716.383, "savedBy": null, "track": "m", "numFloors": "4", "difficulty": "5", "state": "suit", "block": "18"}, "19": {"becameSuitTime": 1551214899.816, "savedBy": null, "track": "m", "numFloors": "3", "difficulty": "3", "state": "suit", "block": "19"}, "13": {"becameSuitTime": 1551214572.518, "savedBy": null, "track": "m", "numFloors": "5", "difficulty": "6", "state": "suit", "block": "13"}}